LePatrick/__init__.py
LePatrick/patrick.py
LePatrick/utils.py
LePatrick/assets/patrick.png
lepatrick-0.1.0.dist-info/METADATA
lepatrick-0.1.0.dist-info/WHEEL
lepatrick-0.1.0.dist-info/top_level.txt
lepatrick-0.1.0.dist-info/RECORD
