Metadata-Version: 2.4
Name: LePatrick
Version: 0.1.0
Summary: Augment images with Patrick imprints.
Author-email: Newton Chen <rfnewton22@gmail.com>, Justin Yu <justinyu1101@gmail.com>
Requires-Python: >=3.10
Requires-Dist: opencv-python==4.9.0.80
Requires-Dist: numpy==1.26.4
